mcp_materials.py
mcp_materials_project-0.3.3.dist-info/METADATA
mcp_materials_project-0.3.3.dist-info/WHEEL
mcp_materials_project-0.3.3.dist-info/entry_points.txt
mcp_materials_project-0.3.3.dist-info/licenses/LICENSE
mcp_materials_project-0.3.3.dist-info/RECORD
