Metadata-Version: 2.4
Name: mcp-materials-project
Version: 0.3.3
Summary: MCP Server for Materials Project database - query material properties, crystal structures, and phase diagrams with horizontal comparison Excel export
Project-URL: Homepage, https://github.com/luffysolution-svg/mcp-materials-project
Project-URL: Repository, https://github.com/luffysolution-svg/mcp-materials-project
Project-URL: Issues, https://github.com/luffysolution-svg/mcp-materials-project/issues
Author: luffysolution-svg
License-Expression: MIT
License-File: LICENSE
Keywords: claude,crystallography,materials-project,materials-science,mcp
Classifier: Development Status :: 4 - Beta
Classifier: Intended Audience :: Science/Research
Classifier: License :: OSI Approved :: MIT License
Classifier: Programming Language :: Python :: 3
Classifier: Programming Language :: Python :: 3.10
Classifier: Programming Language :: Python :: 3.11
Classifier: Programming Language :: Python :: 3.12
Classifier: Programming Language :: Python :: 3.13
Classifier: Topic :: Scientific/Engineering :: Chemistry
Classifier: Topic :: Scientific/Engineering :: Physics
Requires-Python: >=3.10
Requires-Dist: fastmcp>=0.1.0
Requires-Dist: mp-api>=0.39.0
Requires-Dist: openpyxl>=3.1.0
Requires-Dist: pandas>=2.0.0
Requires-Dist: pymatgen>=2024.1.0
